slag/__init__.py
slag/__main__.py
slag/css/github.css
slag/css/main.css
slag/css/normalize.css
slag/css/pygments.css
slag/css/skeleton.css
slag/html/base.html
slag/html/list.html
slag-0.4.0.dist-info/entry_points.txt
slag-0.4.0.dist-info/LICENSE
slag-0.4.0.dist-info/WHEEL
slag-0.4.0.dist-info/METADATA
slag-0.4.0.dist-info/RECORD
