Metadata-Version: 2.1
Name: slag
Version: 0.4.0
Summary: A distributed micro-blog social network on the blockchain.
Home-page: https://github.com/scizzorz/slag
License: MIT
Author: John Weachock
Author-email: jweachock@gmail.com
Requires-Python: >=3.7,<4.0
Classifier: License :: OSI Approved :: MIT License
Classifier: Programming Language :: Python :: 3
Classifier: Programming Language :: Python :: 3.7
Requires-Dist: Jinja2 (>=2.10.1,<3.0.0)
Requires-Dist: Markdown (>=3.1,<4.0)
Requires-Dist: Pygments (>=2.4,<3.0)
Requires-Dist: attrs (>=19.1,<20.0)
Requires-Dist: click (>=7.0,<8.0)
Requires-Dist: pygit2 (==0.27.4)
Requires-Dist: toml (>=0.10.0,<0.11.0)
Project-URL: Repository, https://github.com/scizzorz/slag
